pycricketpred/__init__.py
pycricketpred/data_cleaning.py
pycricketpred/data_wrangling.py
pycricketpred/eda.py
pycricketpred/modelling.py
pycricketpred-0.1.1.dist-info/LICENSE
pycricketpred-0.1.1.dist-info/METADATA
pycricketpred-0.1.1.dist-info/WHEEL
pycricketpred-0.1.1.dist-info/RECORD
