Metadata-Version: 2.1
Name: pycricketpred
Version: 0.1.1
Summary: A package for predicting and find interesting cricket related statistics!
License: MIT
Author: DSCI 310 Group 11: Alex Lin, Jackson Siemens, Shruti Vijaykumar Seetharam, Hanlin Zhao
Requires-Python: >=3.9,<4.0
Classifier: License :: OSI Approved :: MIT License
Classifier: Programming Language :: Python :: 3
Classifier: Programming Language :: Python :: 3.9
Classifier: Programming Language :: Python :: 3.10
Classifier: Programming Language :: Python :: 3.11
Classifier: Programming Language :: Python :: 3.12
Requires-Dist: altair (==5.2.0)
Requires-Dist: click (==8.1.7)
Requires-Dist: jupyterlab (==4.1.4)
Requires-Dist: matplotlib (==3.8.3)
Requires-Dist: numpy (==1.26.4)
Requires-Dist: pandas (==2.2.1)
Requires-Dist: pyarrow (==15.0.1)
Requires-Dist: pytest (==8.1.1)
Requires-Dist: pytest-cov (==5.0.0)
Requires-Dist: scikit-learn (==1.2.0)
Requires-Dist: sphinx (>=7.2.6,<8.0.0)
Requires-Dist: vegafusion (==1.6.5)
Requires-Dist: vegafusion-python-embed (==1.6.6)
Requires-Dist: vl-convert-python (==1.2.3)
